{
    "almostFinished": "Neredeyse bitti",
    "deadline": "Son tarih ",
    "section": "Bölüm ",
    "employee": "Çalışan ",
    "manager": "Yönetici ",
    "remindLater": "Sonra hatırlat",
    "employeeAlert": "Çalışan uyarısı",
        "quickAddition": "Hızlı ekleme",
        "task": "Görev",
        "meeting": "Toplantı",
        "personalInformation": "Kişisel Bilgiler",
        "name": "Ad",
        "nationalNumber": "Ulusal Numara",
        "email": "E-posta",
        "phone": "Telefon",
        "birthDate" : "Dogum Tarihi",
        "birthOfDate": "Doğum Tarihi",
        "duration": "Süre",
        "yearsOfExperience": "Deneyim Yılı",
        "contractType": "Sözleşme Türü",
        "managerFile": "Yönetici Dosyası",
        "functionalSpecialization": "Fonksiyonel Uzmanlık",
        "medical": "Tıp",
        "tourism": "Turizm",
        "engineering": "Mühendislik",
        "commerce": "Ticaret",
        "realEstate": "Emlak",
        "graphics": "Grafikler",
        "addManager": "Yönetici Ekle",
        "addEmployee": "Çalışan Ekle",
        "addTask": "Görev Ekle",
        "inboxMessage" : "Gelen Kutusu"
      
  }
  